{
    "comentarios": [
        {
            "nome": "Carlos Eduardo",
            "descricao": "Lorem ipsum dolor sit amet consectetur, adipisicing elit. Quasi natus id saepe iste, laborum dignissimos accusamus ipsum adipisci aspernatur praesentium, neque ab ullam labore minima. Quae voluptate quas iusto placeat!"
        },
        {
            "nome": "Marcus",
            "descricao": "Otimo"
        },
        {
            "nome": "Maria",
            "descricao": "Incrivel"
        },
        {
            "nome": "andre",
            "descricao": "absasduahsudahsd"
        },
        {
            "nome": "joao",
            "descricao": "Otimo"
        },
        {
            "nome": "pedro",
            "descricao": "Incrivel"
        }
    ]
}